pyslope/__init__.py
pyslope/_version.py
pyslope/cli.py
pyslope/data_validation.py
pyslope/pyslope.py
pyslope/speed_benchmark.py
pyslope/utilities.py
pyslope/docs/Makefile
pyslope/docs/conf.py
pyslope/docs/docstrings.rst
pyslope/docs/examples.rst
pyslope/docs/index.rst
pyslope/docs/installation.rst
pyslope/docs/make.bat
pyslope/docs/requirements_docs.txt
pyslope/examples/readme_example.ipynb
pyslope/examples/readme_example_plot_all_maxfos2.png
pyslope/examples/readme_example_plot_boundary.png
pyslope/examples/readme_example_plot_critical.png
pyslope/examples/readme_example_plot_dynamic.png
pyslope/examples/search.xlsx
pyslope/examples/slices.xlsx
pyslope/examples/summary_results.xlsx
pyslope/examples/validation.ipynb
pyslope/examples/hyrcan/a.hjs
pyslope/examples/hyrcan/b.hjs
pyslope/examples/hyrcan/c.hjs
pyslope/examples/hyrcan/d.hjs
pyslope/examples/hyrcan/e.hjs
pyslope/examples/hyrcan/hyrcan.png
pyslope/examples/readme_img/limits.png
pyslope/examples/readme_img/lls.png
pyslope/examples/readme_img/materials.png
pyslope/examples/readme_img/plot_all_planes2.png
pyslope/examples/readme_img/plot_boundary.png
pyslope/examples/readme_img/plot_critical.png
pyslope/examples/readme_img/slope.png
pyslope/examples/readme_img/udls.png
pyslope/examples/readme_img/water.png
pyslope/examples/search/pySlope_1000.png
pyslope/examples/search/pySlope_2000.png
pyslope/examples/search/pySlope_5000.png
pyslope/examples/search/slide_1000.png
pyslope/examples/search/slide_2000.png
pyslope/examples/search/slide_5000.png
pyslope/examples/slide/a.slim
pyslope/examples/slide/a_2000.slim
pyslope/examples/slide/b.slim
pyslope/examples/slide/c.slim
pyslope/examples/slide/c2.slim
pyslope/examples/slide/d.slim
pyslope/examples/slide/e.slim
pyslope/examples/slide/f.slim
pyslope/examples/slide/slide.png
pyslope/graphs/graphs.ipynb
pyslope/graphs/sandstone_fill_5m_1_1.html
pyslope/graphs/sandstone_fill_FOS_1.25_for_loads_and_angles.html
pyslope/paper/paper.md
pyslope/paper/pySlope_paper.pdf
pyslope-1.4.0.dist-info/licenses/LICENSE.txt
pyslope-1.4.0.dist-info/METADATA
pyslope-1.4.0.dist-info/WHEEL
pyslope-1.4.0.dist-info/entry_points.txt
pyslope-1.4.0.dist-info/top_level.txt
pyslope-1.4.0.dist-info/RECORD
