Metadata-Version: 2.4
Name: pyslope
Version: 1.4.0
Summary: Python slope stability package
Author-email: Jesse Bonanno <jessebonanno@gmail.com>
License-Expression: MIT
Requires-Python: >=3.7
License-File: LICENSE.txt
Requires-Dist: colour
Requires-Dist: plotly
Requires-Dist: tqdm
Requires-Dist: gunicorn
Requires-Dist: django
Requires-Dist: whitenoise
Requires-Dist: dj-database-url
Requires-Dist: psycopg2-binary
Requires-Dist: pytest
Requires-Dist: pytest-cov
Requires-Dist: kaleido==0.2.1
Requires-Dist: numpy
Dynamic: license-file
